README.md
setup.py
yaml_expressions.egg-info/PKG-INFO
yaml_expressions.egg-info/SOURCES.txt
yaml_expressions.egg-info/dependency_links.txt
yaml_expressions.egg-info/requires.txt
yaml_expressions.egg-info/top_level.txt
yex/__init__.py
yex/yex.py