Metadata-Version: 2.1
Name: yaml-expressions
Version: 0.2.1
Summary: Jinja2 templates for yaml. Make dynamic rules and configs.
Home-page: https://github.com/fagcinsk/yaml-expressions
Author: Mikhail Yudin
Author-email: fagci.nsk@gmail.com
License: MIT
Keywords: yaml jinja2 exptessions template
Platform: UNKNOWN
Classifier: Development Status :: 3 - Alpha
Classifier: Topic :: Utilities
Classifier: License :: OSI Approved :: MIT License
